LICENSE
MANIFEST.in
README.md
README.rst
setup.cfg
setup.py
nanomath/__init__.py
nanomath/nanomath.py
nanomath/test_nanomath.py
nanomath/version.py
nanomath.egg-info/PKG-INFO
nanomath.egg-info/SOURCES.txt
nanomath.egg-info/dependency_links.txt
nanomath.egg-info/requires.txt
nanomath.egg-info/top_level.txt