Metadata-Version: 1.2
Name: nanomath
Version: 0.23.3
Summary: A few simple math function for other Oxford Nanopore processing scripts
Home-page: https://github.com/wdecoster/nanomath
Author: Wouter De Coster
Author-email: decosterwouter@gmail.com
License: GPLv3
Keywords: nanopore sequencing plotting quality control
Platform: UNKNOWN
Classifier: Development Status :: 4 - Beta
Classifier: Intended Audience :: Science/Research
Classifier: Topic :: Scientific/Engineering :: Bio-Informatics
Classifier: License :: OSI Approved :: MIT License
Classifier: Programming Language :: Python :: 3
Classifier: Programming Language :: Python :: 3.3
Classifier: Programming Language :: Python :: 3.4
Classifier: Programming Language :: Python :: 3.5
Requires-Python: >=3
